README.txt
setup.py
Sill_E_Scope.egg-info/PKG-INFO
Sill_E_Scope.egg-info/SOURCES.txt
Sill_E_Scope.egg-info/dependency_links.txt
Sill_E_Scope.egg-info/entry_points.txt
Sill_E_Scope.egg-info/not-zip-safe
Sill_E_Scope.egg-info/requires.txt
Sill_E_Scope.egg-info/top_level.txt
sillescope/__init__.py
sillescope/alsasource.py
sillescope/glringbuffer.py
sillescope/nb.py
sillescope/nbreader.py
sillescope/pygscope.py
sillescope/scope.py
sillescope/sinesource.py