Metadata-Version: 1.0
Name: Sill-E-Scope
Version: 0.1.0
Summary: Trivial Software Oscilloscope
Home-page: https://launchpad.net/sillescope
Author: Mike C. Fletcher
Author-email: mcfletch@vrplumber.com
License: BSD
Keywords: Oscilloscope,PyOpenGL,OpenGL,ALSA
Platform: Linux
Classifier: License :: OSI Approved :: BSD License
Classifier: Programming Language :: Python
Classifier: Intended Audience :: Education
